jsonrpc/server/__init__.py
jsonrpc/server/dispatch.py
jsonrpc/server/adapter/__init__.py
jsonrpc/server/adapter/quart.py
jsonrpc_asyncio_server-0.1.1.dist-info/METADATA
jsonrpc_asyncio_server-0.1.1.dist-info/WHEEL
jsonrpc_asyncio_server-0.1.1.dist-info/top_level.txt
jsonrpc_asyncio_server-0.1.1.dist-info/RECORD
