Metadata-Version: 2.1
Name: jsonrpc-asyncio-server
Version: 0.1.1
Summary: Tools for building JSON-RPC servers using asyncio.
Home-page: https://github.com/mkjpryor/jsonrpc-asyncio-server
Author: Matt Pryor
Author-email: matt.pryor@stfc.ac.uk
License: UNKNOWN
Platform: UNKNOWN
Classifier: Programming Language :: Python
Requires-Dist: pydantic
Requires-Dist: jsonrpc-asyncio-model
Provides-Extra: quart
Requires-Dist: quart ; extra == 'quart'
